importproxy/__init__.py
redthing1-0.1.0.dist-info/METADATA
redthing1-0.1.0.dist-info/WHEEL
redthing1-0.1.0.dist-info/RECORD
