Metadata-Version: 2.4
Name: redthing1
Version: 0.1.0
Summary: a simple way to proxy imports in python
Author-email: Red Thing <redthing1@alt.icu>
Requires-Python: >=3.11
Provides-Extra: dev
Requires-Dist: pytest>=8.4.1; extra == 'dev'
